[
  {
    "id": "match1",
    "team1": "Manchester United",
    "team2": "Liverpool",
    "category": "EPL",
    "link": "https://example.com/highlights/man-utd-vs-liverpool"
  },
  {
    "id": "match2",
    "team1": "Real Madrid",
    "team2": "Barcelona",
    "category": "LaLiga",
    "link": "https://example.com/highlights/real-madrid-vs-barcelona"
  },
  {
    "id": "match3",
    "team1": "Juventus",
    "team2": "Inter Milan",
    "category": "Serie A",
    "link": "https://example.com/highlights/juventus-vs-inter"
  },
  {
    "id": "match4",
    "team1": "Bayern Munich",
    "team2": "Borussia Dortmund",
    "category": "Bundesliga",
    "link": "https://example.com/highlights/bayern-vs-dortmund"
  },
  {
    "id": "match5",
    "team1": "Australia",
    "team2": "India",
    "category": "Cricket",
    "link": "https://example.com/highlights/aus-vs-ind"
  },
  {
    "id": "match6",
    "team1": "Manchester City",
    "team2": "Chelsea",
    "category": "Club World Cup",
    "link": "https://example.com/highlights/man-city-vs-chelsea"
  }
]
